hello_world_pycalrissian/__init__.py
hello_world_pycalrissian/app.py
hello_world_pycalrissian/__pycache__/__init__.cpython-312.pyc
hello_world_pycalrissian/__pycache__/__init__.cpython-38.pyc
hello_world_pycalrissian/__pycache__/app.cpython-312.pyc
hello_world_pycalrissian/__pycache__/app.cpython-38.pyc
hello_world_pycalrissian-0.0.9.dist-info/METADATA
hello_world_pycalrissian-0.0.9.dist-info/WHEEL
hello_world_pycalrissian-0.0.9.dist-info/entry_points.txt
hello_world_pycalrissian-0.0.9.dist-info/top_level.txt
hello_world_pycalrissian-0.0.9.dist-info/RECORD
