Metadata-Version: 2.1
Name: hello-world-pycalrissian
Version: 0.0.9
Summary: A very simple Hello world app to submit a job using pycalrissian
Author-email: Parham Membari <parham.membari@terradue.com>
License: MIT
Project-URL: Homepage, https://gitlab.com/pmembari/simple-app-with-pycalrissian
Keywords: pycalrissian,kubernetes
Requires-Dist: click2cwl
Requires-Dist: loguru
Requires-Dist: kubernetes==28.1.0
